{
  "version": "7",
  "dialect": "postgresql",
  "entries": [
    {
      "idx": 0,
      "version": "7",
      "when": 1781011026997,
      "tag": "0000_careless_mole_man",
      "breakpoints": true
    },
    {
      "idx": 1,
      "version": "7",
      "when": 1781016805434,
      "tag": "0001_mean_praxagora",
      "breakpoints": true
    },
    {
      "idx": 2,
      "version": "7",
      "when": 1781030217834,
      "tag": "0002_cloudy_raider",
      "breakpoints": true
    },
    {
      "idx": 3,
      "version": "7",
      "when": 1781031559282,
      "tag": "0003_rainy_mandarin",
      "breakpoints": true
    },
    {
      "idx": 4,
      "version": "7",
      "when": 1781033857520,
      "tag": "0004_burly_lilandra",
      "breakpoints": true
    },
    {
      "idx": 5,
      "version": "7",
      "when": 1781173756622,
      "tag": "0005_deep_patch",
      "breakpoints": true
    },
    {
      "idx": 6,
      "version": "7",
      "when": 1781176677063,
      "tag": "0006_little_sir_ram",
      "breakpoints": true
    },
    {
      "idx": 7,
      "version": "7",
      "when": 1781217744153,
      "tag": "0007_adorable_ares",
      "breakpoints": true
    },
    {
      "idx": 8,
      "version": "7",
      "when": 1781261252948,
      "tag": "0008_odd_excalibur",
      "breakpoints": true
    },
    {
      "idx": 9,
      "version": "7",
      "when": 1781261804764,
      "tag": "0009_thick_bloodstrike",
      "breakpoints": true
    },
    {
      "idx": 10,
      "version": "7",
      "when": 1781278559390,
      "tag": "0010_reflective_stingray",
      "breakpoints": true
    },
    {
      "idx": 11,
      "version": "7",
      "when": 1781313422186,
      "tag": "0011_moaning_blockbuster",
      "breakpoints": true
    },
    {
      "idx": 12,
      "version": "7",
      "when": 1781313441124,
      "tag": "0012_boring_lorna_dane",
      "breakpoints": true
    },
    {
      "idx": 13,
      "version": "7",
      "when": 1781314108751,
      "tag": "0013_sturdy_william_stryker",
      "breakpoints": true
    },
    {
      "idx": 14,
      "version": "7",
      "when": 1781315156651,
      "tag": "0014_noisy_agent_brand",
      "breakpoints": true
    },
    {
      "idx": 15,
      "version": "7",
      "when": 1781349056471,
      "tag": "0015_volatile_deathstrike",
      "breakpoints": true
    },
    {
      "idx": 16,
      "version": "7",
      "when": 1781374195632,
      "tag": "0016_wandering_wolf_cub",
      "breakpoints": true
    },
    {
      "idx": 17,
      "version": "7",
      "when": 1781597091950,
      "tag": "0017_minor_unus",
      "breakpoints": true
    },
    {
      "idx": 18,
      "version": "7",
      "when": 1781683677935,
      "tag": "0018_coords_approx",
      "breakpoints": true
    },
    {
      "idx": 19,
      "version": "7",
      "when": 1781689335913,
      "tag": "0019_serious_rockslide",
      "breakpoints": true
    },
    {
      "idx": 20,
      "version": "7",
      "when": 1781696850371,
      "tag": "0020_huge_ulik",
      "breakpoints": true
    },
    {
      "idx": 21,
      "version": "7",
      "when": 1781704975710,
      "tag": "0021_living_sway",
      "breakpoints": true
    },
    {
      "idx": 22,
      "version": "7",
      "when": 1782125497020,
      "tag": "0022_flaky_luminals",
      "breakpoints": true
    },
    {
      "idx": 23,
      "version": "7",
      "when": 1782155937601,
      "tag": "0023_simple_black_knight",
      "breakpoints": true
    },
    {
      "idx": 24,
      "version": "7",
      "when": 1782179920083,
      "tag": "0024_military_grandmaster",
      "breakpoints": true
    },
    {
      "idx": 25,
      "version": "7",
      "when": 1782629863423,
      "tag": "0025_ai_citations",
      "breakpoints": true
    }
  ]
}